proxywhirl/__init__.py
proxywhirl/browser.py
proxywhirl/cli.py
proxywhirl/config.py
proxywhirl/enrichment.py
proxywhirl/exceptions.py
proxywhirl/exports.py
proxywhirl/fetchers.py
proxywhirl/geo.py
proxywhirl/logging_config.py
proxywhirl/metrics_collector.py
proxywhirl/migrations.py
proxywhirl/premium_sources.py
proxywhirl/py.typed
proxywhirl/rwlock.py
proxywhirl/safe_regex.py
proxywhirl/sources.py
proxywhirl/storage.py
proxywhirl/tui.py
proxywhirl/utils.py
proxywhirl/api/__init__.py
proxywhirl/api/core.py
proxywhirl/api/models.py
proxywhirl/cache/__init__.py
proxywhirl/cache/crypto.py
proxywhirl/cache/manager.py
proxywhirl/cache/models.py
proxywhirl/cache/tiers.py
proxywhirl/circuit_breaker/__init__.py
proxywhirl/circuit_breaker/async_.py
proxywhirl/circuit_breaker/base.py
proxywhirl/circuit_breaker/sync.py
proxywhirl/mcp/__init__.py
proxywhirl/mcp/auth.py
proxywhirl/mcp/server.py
proxywhirl/models/__init__.py
proxywhirl/models/core.py
proxywhirl/rate_limiting/__init__.py
proxywhirl/rate_limiting/limiter.py
proxywhirl/rate_limiting/models.py
proxywhirl/retry/__init__.py
proxywhirl/retry/executor.py
proxywhirl/retry/metrics.py
proxywhirl/retry/policy.py
proxywhirl/rotator/__init__.py
proxywhirl/rotator/async_.py
proxywhirl/rotator/base.py
proxywhirl/rotator/client_pool.py
proxywhirl/rotator/sync.py
proxywhirl/strategies/__init__.py
proxywhirl/strategies/core.py
proxywhirl-0.1.1.dist-info/licenses/LICENSE
proxywhirl-0.1.1.dist-info/METADATA
proxywhirl-0.1.1.dist-info/WHEEL
proxywhirl-0.1.1.dist-info/entry_points.txt
proxywhirl-0.1.1.dist-info/top_level.txt
proxywhirl-0.1.1.dist-info/RECORD
