Metadata-Version: 2.4
Name: proxywhirl
Version: 0.1.1
Summary: Advanced Python proxy rotation library with auto-fetching, validation, and persistence
Author-email: Wyatt Walsh <wyattowalsh@gmail.com>
License: MIT
Project-URL: Homepage, https://github.com/wyattowalsh/proxywhirl
Project-URL: Documentation, https://proxywhirl.readthedocs.io
Project-URL: Repository, https://github.com/wyattowalsh/proxywhirl
Project-URL: Issues, https://github.com/wyattowalsh/proxywhirl/issues
Keywords: proxy,rotation,http,socks,async,fetcher,validator
Classifier: Development Status :: 4 - Beta
Classifier: Intended Audience :: Developers
Classifier: License :: OSI Approved :: MIT License
Classifier: Programming Language :: Python :: 3
Classifier: Programming Language :: Python :: 3.9
Classifier: Programming Language :: Python :: 3.10
Classifier: Programming Language :: Python :: 3.11
Classifier: Programming Language :: Python :: 3.12
Classifier: Programming Language :: Python :: 3.13
Classifier: Topic :: Internet :: Proxy Servers
Classifier: Topic :: Software Development :: Libraries :: Python Modules
Classifier: Typing :: Typed
Requires-Python: >=3.9
License-File: LICENSE
Requires-Dist: httpx>=0.25.0
Requires-Dist: pydantic>=2.0.0
Requires-Dist: pydantic-settings>=2.0.0
Requires-Dist: tenacity>=8.2.0
Requires-Dist: loguru>=0.7.0
Requires-Dist: respx>=0.22.0
Requires-Dist: beautifulsoup4>=4.14.2
Requires-Dist: cryptography>=44.0.1
Requires-Dist: sqlmodel>=0.0.27
Requires-Dist: aiosqlite>=0.21.0
Requires-Dist: greenlet>=3.2.4
Requires-Dist: typer>=0.9.0
Requires-Dist: rich>=13.0.0
Requires-Dist: filelock>=3.12.0
Requires-Dist: platformdirs>=3.0.0
Requires-Dist: tomli-w>=1.0.0
Requires-Dist: tomli>=2.3.0
Requires-Dist: fastapi>=0.100.0
Requires-Dist: uvicorn[standard]>=0.24.0
Requires-Dist: slowapi>=0.1.9
Requires-Dist: python-multipart>=0.0.18
Requires-Dist: portalocker>=2.8.0
Requires-Dist: pyyaml>=6.0.0
Requires-Dist: prometheus-client>=0.19.0
Requires-Dist: httpx-socks>=0.11.0
Requires-Dist: playwright>=1.55.0
Requires-Dist: geoip2>=5.1.0
Requires-Dist: aiofiles>=25.1.0
Requires-Dist: pyrate-limiter>=3.9.0
Requires-Dist: alembic>=1.16.5
Requires-Dist: starlette>=0.49.1
Requires-Dist: aiorwlock>=1.4.0
Requires-Dist: readerwriterlock>=1.0.9
Requires-Dist: aiobreaker>=1.2.0
Provides-Extra: storage
Requires-Dist: sqlmodel>=0.0.14; extra == "storage"
Provides-Extra: security
Requires-Dist: cryptography>=41.0.0; extra == "security"
Provides-Extra: js
Requires-Dist: playwright>=1.40.0; extra == "js"
Provides-Extra: analytics
Requires-Dist: pandas>=2.0.0; extra == "analytics"
Requires-Dist: numpy>=1.24.0; extra == "analytics"
Requires-Dist: scikit-learn>=1.3.0; extra == "analytics"
Provides-Extra: mcp
Requires-Dist: fastmcp>=0.1.0; python_version >= "3.10" and extra == "mcp"
Provides-Extra: all
Requires-Dist: sqlmodel>=0.0.14; extra == "all"
Requires-Dist: cryptography>=41.0.0; extra == "all"
Requires-Dist: playwright>=1.40.0; extra == "all"
Requires-Dist: pandas>=2.0.0; extra == "all"
Requires-Dist: numpy>=1.24.0; extra == "all"
Requires-Dist: scikit-learn>=1.3.0; extra == "all"
Requires-Dist: fastmcp>=0.1.0; python_version >= "3.10" and extra == "all"
Provides-Extra: docs
Requires-Dist: sphinx>=7.4.0; extra == "docs"
Requires-Dist: myst-parser>=2.0.0; extra == "docs"
Requires-Dist: shibuya>=2024.4.0; extra == "docs"
Requires-Dist: sphinx-copybutton>=0.5.2; extra == "docs"
Requires-Dist: sphinx-design>=0.6.0; extra == "docs"
Requires-Dist: sphinxcontrib-mermaid>=0.9.2; extra == "docs"
Requires-Dist: sphinx-docsearch>=0.2.0b3; extra == "docs"
Requires-Dist: linkify-it-py>=2.0.2; extra == "docs"
Provides-Extra: dev
Requires-Dist: pytest>=8.0.0; extra == "dev"
Requires-Dist: pytest-cov>=4.1.0; extra == "dev"
Requires-Dist: pytest-xdist>=3.5.0; extra == "dev"
Requires-Dist: pytest-mock>=3.12.0; extra == "dev"
Requires-Dist: pytest-timeout>=2.2.0; extra == "dev"
Requires-Dist: pytest-benchmark>=4.0.0; extra == "dev"
Requires-Dist: pytest-asyncio>=0.23.0; extra == "dev"
Requires-Dist: pytest-rerunfailures>=13.0; extra == "dev"
Requires-Dist: pytest-watcher>=0.4.0; extra == "dev"
Requires-Dist: pytest-sugar>=1.0.0; extra == "dev"
Requires-Dist: pytest-pretty>=1.2.0; extra == "dev"
Requires-Dist: pytest-html>=4.1.0; extra == "dev"
Requires-Dist: pytest-icdiff>=0.9; extra == "dev"
Requires-Dist: pytest-memray>=1.6.0; extra == "dev"
Requires-Dist: hypothesis>=6.100.0; extra == "dev"
Requires-Dist: syrupy>=4.6.0; extra == "dev"
Requires-Dist: respx>=0.22.0; extra == "dev"
Requires-Dist: polyfactory>=2.15.0; extra == "dev"
Requires-Dist: faker>=24.0.0; extra == "dev"
Requires-Dist: ruff>=0.3.0; extra == "dev"
Requires-Dist: ty>=0.0.7; extra == "dev"
Dynamic: license-file
